ctao_qualpipe-0.2.1.dist-info/licenses/LICENSE
qualpipe/__init__.py
qualpipe/_version.py
qualpipe/version.py
qualpipe/core/__init__.py
qualpipe/core/criterion.py
qualpipe/core/descriptor.py
qualpipe/core/metric.py
qualpipe/tests/__init__.py
qualpipe/tests/data/MonteCarloArray.hdf
qualpipe/tests/data/config.yaml
qualpipe/tests/data/qualpipe.json
qualpipe/tests/unittests/test_criterion.py
qualpipe/tests/unittests/test_descriptor.py
qualpipe/tests/unittests/test_metric.py
qualpipe/tests/unittests/test_tools.py
qualpipe/tests/unittests/test_version.py
qualpipe/tools/__init__.py
qualpipe/tools/metric_evaluator.py
ctao_qualpipe-0.2.1.dist-info/METADATA
ctao_qualpipe-0.2.1.dist-info/WHEEL
ctao_qualpipe-0.2.1.dist-info/entry_points.txt
ctao_qualpipe-0.2.1.dist-info/top_level.txt
ctao_qualpipe-0.2.1.dist-info/RECORD
