Metadata-Version: 2.4
Name: ctao-qualpipe
Version: 0.2.1
Summary: Quality Pipeline, subsystem of DPPS-CTAO
Author-email: Matteo Balbo <matteo.balbo@cta-cosortium.org>, Mykhailo Dalchenko <mykhailo.dalchenko@cta-cosortium.org>, Mikhail Stolpovskiy <mikhail.stolpovskiy@cta-consortium.org>
License: BSD-3-Clause
Project-URL: repository, https://gitlab.cta-observatory.org/cta-computing/dpps/qualpipe/qualpipe
Project-URL: documentation, http://cta-computing.gitlab-pages.cta-observatory.org/dpps/qualpipe/qualpipe
Requires-Python: >=3.10
License-File: LICENSE
Requires-Dist: numpy
Requires-Dist: ctapipe>=0.18
Requires-Dist: h5py
Provides-Extra: test
Requires-Dist: pytest; extra == "test"
Requires-Dist: pytest-cov; extra == "test"
Requires-Dist: pylint>=2.15; extra == "test"
Requires-Dist: black>=22.5; extra == "test"
Requires-Dist: coverage-badge; extra == "test"
Requires-Dist: cwltool; extra == "test"
Requires-Dist: ctapipe_io_lst; extra == "test"
Requires-Dist: llvmlite>=0.44; extra == "test"
Requires-Dist: pytest-requirements; extra == "test"
Provides-Extra: doc
Requires-Dist: sphinx; extra == "doc"
Requires-Dist: pandoc; extra == "doc"
Requires-Dist: numpydoc; extra == "doc"
Requires-Dist: ctao-sphinx-theme; extra == "doc"
Requires-Dist: sphinx-changelog; extra == "doc"
Requires-Dist: myst-parser; extra == "doc"
Requires-Dist: sphinx-paramlinks; extra == "doc"
Requires-Dist: sphinx-argparse; extra == "doc"
Requires-Dist: nbsphinx; extra == "doc"
Requires-Dist: linkify-it-py; extra == "doc"
Provides-Extra: dev
Requires-Dist: setuptools_scm; extra == "dev"
Requires-Dist: towncrier; extra == "dev"
Requires-Dist: pre-commit; extra == "dev"
Provides-Extra: all
Requires-Dist: ctao-qualpipe[dev,doc,test]; extra == "all"
Dynamic: license-file
